deepnull/__init__.py
deepnull/config.py
deepnull/config_test.py
deepnull/data.py
deepnull/data_test.py
deepnull/main.py
deepnull/main_test.py
deepnull/metrics.py
deepnull/metrics_test.py
deepnull/model.py
deepnull/model_test.py
deepnull/train_eval.py
deepnull/train_eval_test.py
deepnull-0.2.2.dist-info/LICENSE
deepnull-0.2.2.dist-info/METADATA
deepnull-0.2.2.dist-info/WHEEL
deepnull-0.2.2.dist-info/top_level.txt
deepnull-0.2.2.dist-info/RECORD
