Metadata-Version: 2.1
Name: deepnull
Version: 0.2.2
Summary: Models nonlinear interactions between covariates and phenotypes
Home-page: https://github.com/google-health/genomics-research/tree/main/nonlinear-covariate-gwas
Author: Google LLC
License: UNKNOWN
Keywords: GWAS
Platform: UNKNOWN
Requires-Python: >=3.7, <4
Requires-Dist: wheel (>=0.36)
Requires-Dist: absl-py (>=0.12)
Requires-Dist: ml-collections (>=0.1)
Requires-Dist: numpy (>=1.19)
Requires-Dist: pandas (>=1.1)
Requires-Dist: tensorflow (>=2.4.1)
Requires-Dist: tensorflow-probability (>=0.12)
Requires-Dist: xgboost (>=1.4)
